amisc-0.8.1.dist-info/METADATA
amisc-0.8.1.dist-info/WHEEL
amisc-0.8.1.dist-info/entry_points.txt
amisc-0.8.1.dist-info/licenses/LICENSE
amisc/__init__.py
amisc/component.py
amisc/compression.py
amisc/distribution.py
amisc/examples/__init__.py
amisc/examples/fire-sat.yml
amisc/examples/models.py
amisc/examples/tutorial.py
amisc/interpolator.py
amisc/serialize.py
amisc/system.py
amisc/training.py
amisc/transform.py
amisc/typing.py
amisc/utils.py
amisc/variable.py
amisc-0.8.1.dist-info/RECORD
