Metadata-Version: 2.1
Name: amisc
Version: 0.8.1
Summary: Efficient framework for building surrogates of multidisciplinary systems using the adaptive multi-index stochastic collocation (AMISC) technique.
Author-Email: Joshua Eckels <eckelsjd@umich.edu>
License: GPL-3.0
Classifier: Programming Language :: Python :: 3
Classifier: Operating System :: OS Independent
Classifier: License :: OSI Approved :: GNU General Public License v3 (GPLv3)
Classifier: Topic :: Scientific/Engineering :: Artificial Intelligence
Classifier: Topic :: Scientific/Engineering :: Mathematics
Classifier: Intended Audience :: Science/Research
Project-URL: Repository, https://github.com/eckelsjd/amisc.git
Project-URL: Documentation, https://eckelsjd.github.io/amisc/
Requires-Python: >=3.11
Requires-Dist: numpy>=2.0
Requires-Dist: scipy>=1.14
Requires-Dist: matplotlib>=3.9
Requires-Dist: networkx>=3.2
Requires-Dist: pyyaml>=6.0.2
Requires-Dist: pydantic!=2.12.*,>=2.9.1
Requires-Dist: dill>=0.3.9
Requires-Dist: scikit-learn>=1.6.1
